fby4.v
//*******************************************************//
//Project name:frequency divide by 2                     //
//Module name: fby2                                      //
//Design version: 1.0                                    //
//Tools used: Synopsys VCS
//Tools version:
//Desctiption:
//Developer name:
//Additional comments:
//******************************************************//

`timescale 1ns/10ps
module fby4(clk,rst, q);
input clk,rst;
output reg q;

reg q1;

always @(posedge (clk)) begin
if(rst)begin
q1 <=0;
q<=0;
$display("D-F/F output",q);
end else begin
q1 <=!q1;
if(q1)begin
q<=!q;
end else begin
q<=q;
end
$display("D-F/F output",q);
end
end
endmodule

tb.v
//***************Frequency divider by 2*****************//
//Project name:
//Module name:
//Design version:
//Tools used:
//Tools version:
//Desctiption:
//Developer name:
//Additional comments:
//******************************************************//

`timescale 1ns/10ps
module tb();
//declaring inputs and output
reg clk, rst;
wire q; 

//instantiating desing module
fby4 f(clk,rst,q);

//providing input stimulus
initial 
clk = 1;
always #5 clk = !clk;
initial begin
rst =1;   
#20 rst =0;

//end simulation at 200ns
#200 $finish; 
end 

//dump variables and generate vcd file to view waveforms
initial begin
$dumpfile("fby4.vcd");
$dumpvars(0,tb);
end



endmodule

fby4.vcd
$date
	Sat Feb  3 16:44:41 2018
$end

$version
	Synopsys VCS version I-2014.03-2
$end

$timescale
	10ps
$end

$comment Csum: 1 d6e23711d426ec9e $end


$scope module tb $end
$var reg 1 ! clk $end
$var reg 1 " rst $end
$var wire 1 # q $end

$scope module f $end
$var wire 1 $ clk $end
$var wire 1 % rst $end
$var reg 1 & q $end
$var reg 1 ' q1 $end
$upscope $end

$upscope $end

$enddefinitions $end

#0
$dumpvars
1!
1$
0&
1%
0#
0'
1"
$end
#500
0!
0$
#1000
1!
1$
#1500
0!
0$
#2000
0"
0%
1!
1$
1'
#2500
0!
0$
#3000
1!
1$
0'
1&
1#
#3500
0!
0$
#4000
1!
1$
1'
#4500
0!
0$
#5000
1!
1$
0'
0&
0#
#5500
0!
0$
#6000
1!
1$
1'
#6500
0!
0$
#7000
1!
1$
0'
1&
1#
#7500
0!
0$
#8000
1!
1$
1'
#8500
0!
0$
#9000
1!
1$
0'
0&
0#
#9500
0!
0$
#10000
1!
1$
1'
#10500
0!
0$
#11000
1!
1$
0'
1&
1#
#11500
0!
0$
#12000
1!
1$
1'
#12500
0!
0$
#13000
1!
1$
0'
0&
0#
#13500
0!
0$
#14000
1!
1$
1'
#14500
0!
0$
#15000
1!
1$
0'
1&
1#
#15500
0!
0$
#16000
1!
1$
1'
#16500
0!
0$
#17000
1!
1$
0'
0&
0#
#17500
0!
0$
#18000
1!
1$
1'
#18500
0!
0$
#19000
1!
1$
0'
1&
1#
#19500
0!
0$
#20000
1!
1$
1'
#20500
0!
0$
#21000
1!
1$
0'
0&
0#
